pathdiff/__about__.py
pathdiff/__init__.py
pathdiff/pathdiff.py
pathdiff-1.0.1.dist-info/METADATA
pathdiff-1.0.1.dist-info/WHEEL
pathdiff-1.0.1.dist-info/entry_points.txt
pathdiff-1.0.1.dist-info/licenses/LICENSE.txt
pathdiff-1.0.1.dist-info/RECORD
