Metadata-Version: 2.1
Name: pathdiff
Version: 1.0.1
Summary: A tool for detecting duplicate files and comparing directories.
Project-URL: Documentation, https://github.com/manvithn/pathdiff#readme
Project-URL: Issues, https://github.com/manvithn/pathdiff/issues
Project-URL: Source, https://github.com/manvithn/pathdiff
Author-email: Manvith Narahari <manvithn@gmail.com>
License-Expression: MIT
License-File: LICENSE.txt
Classifier: Development Status :: 4 - Beta
Classifier: Programming Language :: Python
Classifier: Programming Language :: Python :: 3.7
Classifier: Programming Language :: Python :: 3.8
Classifier: Programming Language :: Python :: 3.9
Classifier: Programming Language :: Python :: 3.10
Classifier: Programming Language :: Python :: 3.11
Classifier: Programming Language :: Python :: Implementation :: CPython
Classifier: Programming Language :: Python :: Implementation :: PyPy
Requires-Python: >=3.7
Requires-Dist: alive-progress
Requires-Dist: click
